teachpyx/__init__.py
teachpyx/ext_test_case.py
teachpyx/datasets/__init__.py
teachpyx/datasets/data_helper.py
teachpyx/datasets/data_ts.py
teachpyx/datasets/documentation.py
teachpyx/datasets/enedis.py
teachpyx/datasets/gpd_helper.py
teachpyx/datasets/wines.py
teachpyx/datasets/data/__init__.py
teachpyx/datasets/data/adult.data.gz
teachpyx/datasets/data/adult.test.gz
teachpyx/datasets/data/countries.geo.json
teachpyx/datasets/data/reunion.zip
teachpyx/datasets/data/reunion_rect.zip
teachpyx/datasets/data/search_tiny_test.txt
teachpyx/datasets/data/search_tiny_train.txt
teachpyx/datasets/data/titanic.txt
teachpyx/datasets/data/titanic3.csv
teachpyx/datasets/data/tweets_macron_sijetaispresident_201609.zip
teachpyx/datasets/data/wine.data.txt
teachpyx/datasets/data/wines-quality.csv
teachpyx/examples/__init__.py
teachpyx/examples/classiques.py
teachpyx/examples/construction_classique.py
teachpyx/examples/numpysex.py
teachpyx/faq/__init__.py
teachpyx/faq/faq_exception.py
teachpyx/faq/faq_geo.py
teachpyx/faq/faq_numpy.py
teachpyx/faq/faq_python.py
teachpyx/practice/__init__.py
teachpyx/practice/ml_skl.py
teachpyx/practice/rues_paris.py
teachpyx/practice/tsp_bresenham.py
teachpyx/practice/tsp_kohonen.py
teachpyx/practice/tsp_kruskal.py
teachpyx/tools/__init__.py
teachpyx/tools/data_helper.py
teachpyx/tools/graphviz_helper.py
teachpyx/tools/helpers.py
teachpyx/tools/pandas.py
teachpyx/tools/profiling.py
teachpyx/tools/display/__init__.py
teachpyx/tools/display/pygame_helper.py
teachpyx/tools/display/video_helper.py
teachpyx/video/__init__.py
teachpyx/video/tsp_kohonen_pygame.py
teachpyx/video/tsp_kruskal_pygame.py
teachpyx-0.5.0.dist-info/licenses/LICENSE.txt
teachpyx-0.5.0.dist-info/METADATA
teachpyx-0.5.0.dist-info/WHEEL
teachpyx-0.5.0.dist-info/top_level.txt
teachpyx-0.5.0.dist-info/RECORD
