Metadata-Version: 2.4
Name: teachpyx
Version: 0.5.0
Summary: Teaching material, algorithm, machine learning
Home-page: https://github.com/sdpython/teachpyx
Author: Xavier Dupré
Author-email: Xavier Dupré <xavier.dupre@gmail.com>
License: ﻿Copyright (c) 2016-2024, Xavier Dupré
Project-URL: Homepage, https://sdpython.github.io/doc/teachpyx/dev/
Project-URL: Documentation, https://sdpython.github.io/doc/teachpyx/dev/
Project-URL: Repository, https://github.com/sdpython/teachpyx/
Project-URL: Changelog, https://github.com/sdpython/teachpyx/blob/main/CHANGELOGS.rst
Project-URL: Issues, https://github.com/sdpython/teachpyx/issues
Keywords: python,teaching,algorithmic,machine learning
Classifier: Intended Audience :: Science/Research
Classifier: Intended Audience :: Developers
Classifier: License :: OSI Approved :: MIT License
Classifier: Programming Language :: C
Classifier: Programming Language :: Python
Classifier: Topic :: Software Development
Classifier: Topic :: Scientific/Engineering
Classifier: Development Status :: 5 - Production/Stable
Classifier: Operating System :: Microsoft :: Windows
Classifier: Operating System :: POSIX
Classifier: Operating System :: Unix
Classifier: Operating System :: MacOS
Classifier: Programming Language :: Python :: 3
Classifier: Programming Language :: Python :: 3.9
Classifier: Programming Language :: Python :: 3.10
Classifier: Programming Language :: Python :: 3.11
Requires-Python: >=3.9
License-File: LICENSE.txt
Requires-Dist: numpy
Requires-Dist: matplotlib
Requires-Dist: pandas
Requires-Dist: scikit-learn>=1.2
Requires-Dist: tqdm
Provides-Extra: dev
Requires-Dist: black; extra == "dev"
Requires-Dist: black-nb; extra == "dev"
Requires-Dist: chardet; extra == "dev"
Requires-Dist: cloudpickle; extra == "dev"
Requires-Dist: coverage; extra == "dev"
Requires-Dist: cytoolz; extra == "dev"
Requires-Dist: dbfread; extra == "dev"
Requires-Dist: dict2xml; extra == "dev"
Requires-Dist: furo; extra == "dev"
Requires-Dist: ipython; extra == "dev"
Requires-Dist: jinja2; extra == "dev"
Requires-Dist: jupyter; extra == "dev"
Requires-Dist: lifelines; extra == "dev"
Requires-Dist: lxml; extra == "dev"
Requires-Dist: matplotlib; extra == "dev"
Requires-Dist: mutagen; extra == "dev"
Requires-Dist: nbsphinx; extra == "dev"
Requires-Dist: networkx; extra == "dev"
Requires-Dist: openpyxl; extra == "dev"
Requires-Dist: pandas; extra == "dev"
Requires-Dist: pillow; extra == "dev"
Requires-Dist: protobuf<4; extra == "dev"
Requires-Dist: pyinstrument; extra == "dev"
Requires-Dist: pytest; extra == "dev"
Requires-Dist: pytest-cov; extra == "dev"
Requires-Dist: ruff; extra == "dev"
Requires-Dist: seaborn; extra == "dev"
Requires-Dist: scikit-image; extra == "dev"
Requires-Dist: sphinx; extra == "dev"
Requires-Dist: sphinx-gallery; extra == "dev"
Requires-Dist: sphinx-issues; extra == "dev"
Requires-Dist: sphinx-runpython; extra == "dev"
Requires-Dist: ujson; extra == "dev"
Requires-Dist: wheel; extra == "dev"
Dynamic: author
Dynamic: home-page
Dynamic: license-file
